wofs/__init__.py
wofs/_version.py
wofs/boilerplate.py
wofs/classifier.py
wofs/constants.py
wofs/filters.py
wofs/terrain.py
wofs/virtualproduct.py
wofs/wofls.py
wofs/wofs_app.py
wofs-1.6.6.data/data/wofs/config/wofs_albers.yaml
wofs-1.6.6.data/data/wofs/config/wofs_modified_albers.yaml
wofs-1.6.6.dist-info/METADATA
wofs-1.6.6.dist-info/WHEEL
wofs-1.6.6.dist-info/entry_points.txt
wofs-1.6.6.dist-info/top_level.txt
wofs-1.6.6.dist-info/RECORD
