Metadata-Version: 2.1
Name: wofs
Version: 1.6.6
Summary: Water Observations from Space - Digital Earth Australia
Home-page: https://github.com/GeoscienceAustralia/wofs
Author: Geoscience Australia
Maintainer: Geoscience Australia
Maintainer-email: 
License: Apache License 2.0
Classifier: Development Status :: 4 - Beta
Classifier: Intended Audience :: Science/Research
Classifier: License :: OSI Approved :: Apache Software License
Classifier: Programming Language :: Python :: 3.6
Classifier: Operating System :: OS Independent
Classifier: Intended Audience :: Developers
Classifier: Topic :: Scientific/Engineering :: GIS
Classifier: Topic :: Scientific/Engineering :: Information Analysis
Requires-Dist: datacube
Requires-Dist: scipy
Requires-Dist: ephem
Requires-Dist: xarray >=0.14.1
Provides-Extra: test
Requires-Dist: pytest ; extra == 'test'
Requires-Dist: pytest-cov ; extra == 'test'
Requires-Dist: mock ; extra == 'test'
Requires-Dist: pylint ; extra == 'test'
Requires-Dist: hypothesis ; extra == 'test'
Requires-Dist: compliance-checker ; extra == 'test'
Requires-Dist: black ; extra == 'test'
